_lab/__init__.py
_lab/test_d2.py
_lab/test_d3.py
_lab/test_d4.py
_lab/test_d5.py
_lab/test_disk.py
_lab/test_read_data.py
_lab/test_web.py
plotmanx/__init__.py
plotmanx/__main__.py
plotmanx/archive.py
plotmanx/chia.py
plotmanx/clockwork.py
plotmanx/configuration.py
plotmanx/err.py
plotmanx/farmplot.py
plotmanx/interactive.py
plotmanx/job.py
plotmanx/maint.py
plotmanx/manager.py
plotmanx/plotman.py
plotmanx/reporting.py
plotmanx/_tests/__init__.py
plotmanx/_tests/analyze_test.py
plotmanx/_tests/archive_test.py
plotmanx/_tests/configuration_test.py
plotmanx/_tests/job_test.py
plotmanx/_tests/manager_test.py
plotmanx/_tests/plot_util_test.py
plotmanx/_tests/reporting_test.py
plotmanx/_tests/resources/__init__.py
plotmanx/analyze/__init__.py
plotmanx/analyze/pri.py
plotmanx/analyze/report.py
plotmanx/query/__init__.py
plotmanx/query/api.py
plotmanx/query/servefiles.py
plotmanx/query/sql.py
plotmanx/resources/__init__.py
plotmanx/util/__init__.py
plotmanx/util/plot_util.py
plotmanx/util/send_notification.py
plotmanx/util/yamlgen.py
plotmanx-0.6.54.data/data/bin/listlogs
plotmanx-0.6.54.data/data/config/plotman.yaml
plotmanx-0.6.54.dist-info/LICENSE
plotmanx-0.6.54.dist-info/METADATA
plotmanx-0.6.54.dist-info/WHEEL
plotmanx-0.6.54.dist-info/entry_points.txt
plotmanx-0.6.54.dist-info/top_level.txt
plotmanx-0.6.54.dist-info/RECORD
