Metadata-Version: 2.1
Name: plotmanx
Version: 0.6.54
Summary: Chia plotting manager
Home-page: https://github.com/ericaltendorf/plotman
Author: Eric Altendorf and Heskemo
License: Apache 2.0
Project-URL: Bug Tracker, https://github.com/ericaltendorf/plotman/issues
Project-URL: Changelog, https://github.com/ericaltendorf/plotman/blob/main/CHANGELOG.md
Keywords: chia,blockchain,automation,process management
Platform: UNKNOWN
Classifier: Development Status :: 3 - Alpha
Classifier: Environment :: Console :: Curses
Classifier: Intended Audience :: Developers
Classifier: Intended Audience :: System Administrators
Classifier: Intended Audience :: Information Technology
Classifier: License :: OSI Approved :: Apache Software License
Classifier: Natural Language :: English
Classifier: Operating System :: POSIX :: Linux
Classifier: Operating System :: MacOS :: MacOS X
Classifier: Programming Language :: Python :: 3
Classifier: Programming Language :: Python :: Implementation :: CPython
Classifier: Programming Language :: Python :: Implementation :: PyPy
Classifier: Topic :: System :: Monitoring
Classifier: Topic :: System :: Systems Administration
Classifier: Topic :: Utilities
Requires-Dist: appdirs
Requires-Dist: click
Requires-Dist: desert
Requires-Dist: marshmallow
Requires-Dist: pendulum
Requires-Dist: psutil (~=5.8)
Requires-Dist: pyyaml
Requires-Dist: texttable
Requires-Dist: tornado
Requires-Dist: requests
Requires-Dist: prometheus-client
Requires-Dist: xlsxwriter
Provides-Extra: dev
Requires-Dist: check-manifest ; extra == 'dev'
Requires-Dist: pytest ; extra == 'dev'
Requires-Dist: pytest-mock ; extra == 'dev'
Requires-Dist: pyfakefs ; extra == 'dev'
Requires-Dist: isort ; extra == 'dev'
Provides-Extra: test
Requires-Dist: check-manifest ; extra == 'test'
Requires-Dist: pytest ; extra == 'test'
Requires-Dist: pytest-mock ; extra == 'test'
Requires-Dist: pyfakefs ; extra == 'test'
